setup.py
wapiti/__init__.py
wapiti/client.py
wapiti/compat.py
wapiti/ransom.py
wapiti/tests.py
wapiti.egg-info/PKG-INFO
wapiti.egg-info/SOURCES.txt
wapiti.egg-info/dependency_links.txt
wapiti.egg-info/not-zip-safe
wapiti.egg-info/top_level.txt
wapiti/operations/__init__.py
wapiti/operations/base.py
wapiti/operations/category.py
wapiti/operations/conftest.py
wapiti/operations/feedback.py
wapiti/operations/files.py
wapiti/operations/links.py
wapiti/operations/meta.py
wapiti/operations/misc.py
wapiti/operations/models.py
wapiti/operations/params.py
wapiti/operations/protection.py
wapiti/operations/query_operations.py
wapiti/operations/rand.py
wapiti/operations/revisions.py
wapiti/operations/template_parser.py
wapiti/operations/templates.py
wapiti/operations/test_basic.py
wapiti/operations/test_operations.py
wapiti/operations/user.py
wapiti/operations/utils.py