Metadata-Version: 1.1
Name: wapiti
Version: 0.1
Summary: A Wikipedia API client for humans and elk.
Home-page: https://github.com/mahmoud/wapiti
Author: Mahmoud Hashemi
Author-email: mahmoudrhashemi@gmail.com
License: BSD
Platform: any
Classifier: Intended Audience :: Developers
Classifier: Topic :: Software Development :: Libraries
Classifier: Programming Language :: Python :: 2.6
Classifier: Programming Language :: Python :: 2.7
Classifier: Topic :: Internet :: WWW/HTTP
Classifier: Topic :: Education
Classifier: Development Status :: 3 - Alpha
